fluent_comments/__init__.py
fluent_comments/admin.py
fluent_comments/akismet.py
fluent_comments/apps.py
fluent_comments/appsettings.py
fluent_comments/email.py
fluent_comments/models.py
fluent_comments/moderation.py
fluent_comments/receivers.py
fluent_comments/urls.py
fluent_comments/utils.py
fluent_comments/views.py
fluent_comments/forms/__init__.py
fluent_comments/forms/_captcha.py
fluent_comments/forms/base.py
fluent_comments/forms/captcha.py
fluent_comments/forms/compact.py
fluent_comments/forms/default.py
fluent_comments/forms/helper.py
fluent_comments/forms/recaptcha.py
fluent_comments/locale/cs/LC_MESSAGES/django.mo
fluent_comments/locale/cs/LC_MESSAGES/django.po
fluent_comments/locale/nl/LC_MESSAGES/django.mo
fluent_comments/locale/nl/LC_MESSAGES/django.po
fluent_comments/locale/sk/LC_MESSAGES/django.mo
fluent_comments/locale/sk/LC_MESSAGES/django.po
fluent_comments/locale/zh/LC_MESSAGES/django.mo
fluent_comments/locale/zh/LC_MESSAGES/django.po
fluent_comments/migrations/0001_initial.py
fluent_comments/migrations/__init__.py
fluent_comments/static/fluent_comments/css/ajaxcomments.css
fluent_comments/static/fluent_comments/img/ajax-wait.gif
fluent_comments/static/fluent_comments/js/ajaxcomments.js
fluent_comments/templates/comments/comment.html
fluent_comments/templates/comments/comment_notification_email.html
fluent_comments/templates/comments/comment_notification_email.txt
fluent_comments/templates/comments/deleted.html
fluent_comments/templates/comments/flagged.html
fluent_comments/templates/comments/form.html
fluent_comments/templates/comments/list.html
fluent_comments/templates/comments/posted.html
fluent_comments/templates/comments/preview.html
fluent_comments/templates/fluent_comments/templatetags/ajax_comment_tags.html
fluent_comments/templates/fluent_comments/templatetags/flat_list.html
fluent_comments/templates/fluent_comments/templatetags/threaded_list.html
fluent_comments/templatetags/__init__.py
django_fluent_comments-3.0.dist-info/AUTHORS
django_fluent_comments-3.0.dist-info/LICENSE
django_fluent_comments-3.0.dist-info/METADATA
django_fluent_comments-3.0.dist-info/WHEEL
django_fluent_comments-3.0.dist-info/top_level.txt
django_fluent_comments-3.0.dist-info/RECORD
