Metadata-Version: 2.1
Name: django-fluent-comments
Version: 3.0
Summary: A modern, ajax-based appearance for django_comments
Home-page: https://github.com/edoburu/django-fluent-comments
Author: Diederik van der Boor
Author-email: opensource@edoburu.nl
License: Apache 2.0
Download-URL: https://github.com/edoburu/django-fluent-comments/zipball/master
Platform: UNKNOWN
Classifier: Development Status :: 5 - Production/Stable
Classifier: Environment :: Web Environment
Classifier: Framework :: Django
Classifier: Intended Audience :: Developers
Classifier: License :: OSI Approved :: Apache Software License
Classifier: Operating System :: OS Independent
Classifier: Programming Language :: Python
Classifier: Programming Language :: Python :: 3.7
Classifier: Programming Language :: Python :: 3.8
Classifier: Programming Language :: Python :: 3.9
Classifier: Framework :: Django
Classifier: Framework :: Django :: 2.2
Classifier: Framework :: Django :: 3.0
Classifier: Framework :: Django :: 3.1
Classifier: Framework :: Django :: 3.2
Classifier: Topic :: Internet :: WWW/HTTP
Classifier: Topic :: Internet :: WWW/HTTP :: Dynamic Content
Classifier: Topic :: Software Development :: Libraries :: Application Frameworks
Classifier: Topic :: Software Development :: Libraries :: Python Modules
Requires: Django (>=2.2)
Requires-Dist: django-crispy-forms (>=1.9.2)
Requires-Dist: django-tag-parser (>=3.2)
Requires-Dist: django-contrib-comments (>=2.0.0)
Requires-Dist: python-akismet (>=0.4.1)
Provides-Extra: threadedcomments
Requires-Dist: django-threadedcomments (>=1.2) ; extra == 'threadedcomments'
